[
  {
    "id": 25,
    "date": "2024.07.19",
    "title": "◥◣#関ケ原唄姫合戦2024 オフィシャルグッズ情報💥◢◤",
    "context": [
      "",
      "イベント公式GOODSを販売してます！",
      "",
      "クローク横で販売していますので、ぜひお立ち寄りください！",
      "",
      "",
      ""
    ],
    "urls": [],
    "img": [
      "https://sekigahara-idolwars.net/images/2024/goods/goods.png",
      "https://sekigahara-idolwars.net/images/2024/goods/doods_pic1.jpg",
      "https://sekigahara-idolwars.net/images/2024/goods/goods_pic2.jpg"
    ]
  },
  {
    "id": 24,
    "date": "2024.07.19",
    "title": "徳川ステージ配信決定💥",
    "context": [
      "",
      "徳川ステージをMETALIVEで生配信決定！",
      "",
      "METALIVE視聴はこちら👇",
      "",
      "※視聴料金　1DAY ¥2,500 / 💎2,273",
      "",
      ""
    ],
    "urls": [
      {
        "title": "METALIVE",
        "url": "https://user.meta-live.jp/topics/47"
      }
    ],
    "img": ["https://sekigahara-idolwars.net/images/2024/news/news24.jpg"]
  },
  {
    "id": 23,
    "date": "2024.07.18",
    "title": "関ケ原唄姫合戦-10thAnniversary-開催記念！WithLIVEくじを開催🎂",
    "context": [
      "",
      "描き下ろしアートや過去デザインを使用した、ここでしか手に入らない豪華限定景品が盛りだくさん🎁✨ ",
      "",
      "SS賞は超レア❗️10周年を記念した、このくじだけのオリジナルデザインTシャツ🙌",
      "",
      "S賞は思い出を飾れる、オリジナルデザインのA5サイズフォトパネル📷",
      "",
      "10連特典有💞のぼりデザインステッカーがランダムで当たります🌟",
      "",
      "ぜひお目当ての景品をゲットしてください✨",
      "",
      "❤️‍🔥Wチャンス賞❤️‍🔥",
      "10連を引いた方の中から”抽選”で20名様に関ケ原出演者の直筆サイン入りのぼりが当たります🎯 "
    ],
    "urls": [
      {
        "title": "With Live",
        "url": "https://withlive.jp/kuji.php?id=7958"
      }
    ],
    "img": ["https://sekigahara-idolwars.net/images/2024/news/news23.jpg"]
  },
  {
    "id": 22,
    "date": "2024.07.18",
    "title": "エリアマップ公開💥",
    "context": ["", "お待たせしました!! ", "エリアマップ公開🗾", "", ""],
    "urls": [
      {
        "title": "TIGET",
        "url": "https://tiget.net/events/330277"
      }
    ],
    "img": ["https://sekigahara-idolwars.net/images/2024/map/map.jpg"]
  },
  {
    "id": 21,
    "date": "2024.07.18",
    "title": "物販タイムテーブル発表💥",
    "context": [
      "",
      "物販タイムテーブルの最新版です。",
      "何ヶ所か変更もありますのでお目当ての特典会をチェック☑️",
      "",
      "アイドルさんたちと一緒に楽しもう！！",
      ""
    ],
    "urls": [
      {
        "title": "TIGET",
        "url": "https://tiget.net/events/330277"
      }
    ],
    "img": [
      "https://sekigahara-idolwars.net/images/2024/news/news21_1.jpg",
      "https://sekigahara-idolwars.net/images/2024/news/news21_2.jpg",
      "https://sekigahara-idolwars.net/images/2024/news/news21_3.jpg"
    ]
  },
  {
    "id": 20,
    "date": "2024.07.18",
    "title": "物販タイムテーブル発表💥",
    "context": [
      "",
      "熱い熱い３日間にしよう!!",
      "特別な夏の思い出を作りましょう✨",
      "",
      "",
      "アイドルさんたちと一緒に楽しもう！！",
      ""
    ],
    "urls": [
      {
        "title": "TIGET",
        "url": "https://tiget.net/events/330277"
      }
    ],
    "img": [
      "https://sekigahara-idolwars.net/images/2024/news/news20_1.jpg",
      "https://sekigahara-idolwars.net/images/2024/news/news20_2.jpg",
      "https://sekigahara-idolwars.net/images/2024/news/news20_3.jpg"
    ]
  },
  {
    "id": 19,
    "date": "2024.07.15",
    "title": "ちぃたん☆出陣決定💥",
    "context": [
      "",
      "今年も関ケ原唄姫合戦応援大使 ちぃたん☆ がやってくる💥",
      "",
      "ちぃたん☆の気分でお散歩したり遊んだりステージ乱入も⁉️",
      "などなどイベントを盛り上げます！",
      "",
      "💃参加アイドル運営様へ⬇️",
      "ちぃたん☆乱入希望の方は直接お声がけください^ ^",
      "",
      ""
    ],
    "urls": [],
    "img": ["https://sekigahara-idolwars.net/images/2024/home/news19.jpg"]
  },
  {
    "id": 18,
    "date": "2024.07.14",
    "title": "#関ケ原唄姫合戦2024 特別企画第一弾💥",
    "context": [
      "",
      "7/20(土) 徳川ステージにて矢口真里さんとのスペシャルコラボが決定！",
      "",
      "記念すべき10回目開催となる本公演の特別企画として、",
      "何と！モーニング娘。OG矢口真里さんが、お祝いに駆け付けます！",
      "",
      "コーナーMCと、SEKIGAHARA IDOL WARSに出演する選抜メンバーと国民的ヒット曲をコラボ！ ",
      "",
      "コラボ曲は、お楽しみに🎶",
      ""
    ],
    "urls": [],
    "img": ["https://sekigahara-idolwars.net/images/2024/home/home10.jpg"]
  },
  {
    "id": 17,
    "date": "2024.07.14",
    "title": "#関ケ原唄姫合戦2024 シャトルバス情報🚗",
    "context": [
      "",
      "今年もシャトルバス🚌運行します✨",
      "JR 関ケ原駅⇆桃配運動公園",
      "🎫料金:片道 ¥500-",
      "",
      "※電子決済は対応しておりませんので現金でお支払いをお願いいたします。",
      "※天候、道路交通障害等による発着時間が遅延することもあります。悪しからずご了承ください。",
      "",
      ""
    ],
    "urls": [],
    "img": ["https://sekigahara-idolwars.net/images/2024/home/access2.jpg"]
  },
  {
    "id": 16,
    "date": "2024.07.14",
    "title": "#関ケ原唄姫合戦2024 駐車場情報🚗",
    "context": [
      "",
      "🔵第一駐車場(関ケ原唄姫合戦2024 会場隣接)",
      "第一駐車場は、駐車場利用の際は、チケットの購入が必須となります。",
      "",
      "■販売 TIGET先着販売",
      "https://tiget.net/events/333907",
      "7/19 駐車場チケット 7月15日(月祝) 12:30-7月18日(木)23:59",
      "7/20 駐車場チケット 7月15日(月祝) 12:45-7月19日(金)23:59",
      "7/21 駐車場チケット 7月15日(月祝) 13:00-7月20日(土)23:59",
      "",
      "■時間　第一駐車場利用時間",
      "一日目(7/19)＞8:00-21:40",
      "二日目(7/20)＞7:30-21:40",
      "三日目(7/21)＞7:30-21:10",
      "",
      "",
      "🔵第二駐車場 ",
      "各日 無料で利用可能 ",
      "※駐車できる台数は、限りがございます。",
      ""
    ],
    "urls": [
      {
        "title": "販売 TIGET先着販売",
        "url": "https://tiget.net/events/333907"
      }
    ],
    "img": ["https://sekigahara-idolwars.net/images/2024/home/access1.jpg"]
  },
  {
    "id": 15,
    "date": "2024.07.13",
    "title": "関ケ原唄姫合戦2024 サテライトイベントタイムテーブル公開💥",
    "context": [
      "",
      "2024年7月20日(土)",
      "『関ケ原唄姫合戦サテライトイベント〜徳川？豊臣？いやいや岐阜は織田じゃ〜 DAY／Night』",
      "at 岐阜club-G",
      "",
      "",
      "🎟️A／B チケット2000円 ※D代別途",
      "",
      "",
      "【DAY】",
      "OPEN9:30　START10:00",
      "TIGET先着販売7/15(月祝)11:00〜",
      "",
      "JAPANARIZM／テンシメシ／UPローチ／【eN】／MATANAGOYA／TEARS-ティアーズ-／にとくり。／Sistersあにま／P-Loco／ミスティア／東京Cute School ／Re:Clash(Candy☆Drops)",
      "",
      "",
      "【NIGHT】",
      "OPEN15:10　START15:30",
      "7/15(月祝)11:30〜7/19(金)23:59",
      "",
      "JAPANARIZM／テンシメシ／UPローチ／【eN】／MATANAGOYA／TEARS-ティアーズ-／にとくり。／Sistersあにま／P-Loco／NEO BREAK／ЯiＭ：ＭiＲ／蜂蜜★皇帝／アステリア／究極人形",
      ""
    ],
    "urls": [
      {
        "title": "DAYチケット",
        "url": "https://tiget.net/events/333571"
      },
      {
        "title": "NIGHTチケット",
        "url": "https://tiget.net/events/333572"
      }
    ],
    "img": [
      "https://sekigahara-idolwars.net/images/2024/home/home8.jpg",
      "https://sekigahara-idolwars.net/images/2024/home/home9.jpg"
    ]
  },
  {
    "id": 14,
    "date": "2024.07.12",
    "title": "関ケ原唄姫合戦2024 サテライトイベント開催💥",
    "context": [
      "",
      "2024年7月20日(土)",
      "『関ケ原唄姫合戦サテライトイベント〜徳川？豊臣？いやいや岐阜は織田じゃ〜 DAY／Night』",
      "at 岐阜club-G",
      "",
      "",
      "🎟️A／B チケット2000円 ※D代別途",
      "",
      "",
      "【DAY】",
      "OPEN9:30　START10:00",
      "TIGET先着販売7/15(月祝)11:00〜",
      "",
      "JAPANARIZM／テンシメシ／UPローチ／【eN】／MATANAGOYA／TEARS-ティアーズ-／にとくり。／Sistersあにま／P-Loco／ミスティア／東京Cute School ／Re:Clash(Candy☆Drops)",
      "",
      "",
      "【NIGHT】",
      "OPEN15:10　START15:30",
      "7/15(月祝)11:30〜7/19(金)23:59",
      "",
      "JAPANARIZM／テンシメシ／UPローチ／【eN】／MATANAGOYA／TEARS-ティアーズ-／にとくり。／Sistersあにま／P-Loco／NEO BREAK／ЯiＭ：ＭiＲ／蜂蜜★皇帝／アステリア／究極人形",
      ""
    ],
    "urls": [
      {
        "title": "DAYチケット",
        "url": "https://tiget.net/events/333571"
      },
      {
        "title": "NIGHTチケット",
        "url": "https://tiget.net/events/333572"
      }
    ],
    "img": ["https://sekigahara-idolwars.net/images/2024/home/home8.jpg"]
  },
  {
    "id": 13,
    "date": "2024.07.09",
    "title": "関ケ原唄姫合戦2024予戦会 最終決戦 各ブロック結果発表",
    "context": [
      "",
      "徳川ステージを勝ち取ったのは、この唄姫だ!!",
      "",
      "Aブロック",
      "LOVE 9 LOVE",
      "",
      "Bブロック",
      "OS☆K",
      "",
      "Cブロック",
      "ミラクルファンファーレ！",
      "",
      "Dブロック",
      "Cent Heaven",
      ""
    ],
    "urls": [],
    "img": ["https://sekigahara-idolwars.net/images/2024/home/news13.jpg"]
  },
  {
    "id": 12,
    "date": "2024.07.09",
    "title": "ロードモバイル布陣として勝ち抜いた4組 出陣決定",
    "context": [
      "",
      "ロードモバイル布陣として勝ち抜いた4組 出陣決定",
      "",
      "1位：Glim Assembler（20,21）",
      "2位：SAI²Rium（20,21）",
      "3位：LOVEME（20）",
      "4位：ポラライト（21）",
      ""
    ],
    "urls": [],
    "img": ["https://sekigahara-idolwars.net/images/2024/home/news12.jpg"]
  },
  {
    "id": 11,
    "date": "2024.06.28",
    "title": "各出演日修正・追加発表",
    "context": [
      "",
      "出演者追加",
      "",
      "アステリア（21）／夜宙☆ShiNew’（19,20）／彗星♩droptune°（20,21）／ナト☆カン（20）／ヤンチャン学園音楽部（19,20）",
      ""
    ],
    "urls": [],
    "img": ["https://sekigahara-idolwars.net/images/2024/home/news11.jpg"]
  },
  {
    "id": 10,
    "date": "2024.06.27",
    "title": "#関ケ原唄姫合戦2024 注意事項",
    "context": ["", "関ケ原唄姫合戦を楽しむ為に皆様お守りください", ""],
    "urls": [],
    "img": ["https://sekigahara-idolwars.net/images/2024/home/notice.jpg"]
  },
  {
    "id": 9,
    "date": "2024.06.27",
    "title": "#関ケ原唄姫合戦2024 チケット詳細",
    "context": [
      "",
      "チケット詳細発表",
      "",
      "",
      "TIGET先着販売 https://tiget.net/events/330277",
      "",
      "プレミアチケット販売受付期間:6/29(土)11:00〜各公演日の前日22:00",
      "",
      "一般チケット販売受付期間:6/29(土)12:00〜各公演日の前日22:00"
    ],
    "urls": [
      {
        "title": "チケットページ",
        "url": "https://tiget.net/events/330277"
      }
    ],
    "img": ["https://sekigahara-idolwars.net/images/2024/home/ticket.jpg"]
  },
  {
    "id": 8,
    "date": "2024.06.26",
    "title": "【第七布陣】出演者発表!!",
    "context": [
      "",
      "第七布陣として予戦会を勝ち抜いた10組 出陣決定！",
      "",
      "",
      "ideal peco／あくまで天使／UNBS／SIR確変中／Sistersあにま／TEARS-ティアーズ-／にとくり。／ベロティカ／瞬きもせず／マーキュロ (五十音順)"
    ],
    "urls": [],
    "img": ["https://sekigahara-idolwars.net/images/2024/home/home7.jpg"]
  },
  {
    "id": 7,
    "date": "2024.06.25",
    "title": "【第六布陣】出演者発表!!",
    "context": [
      "",
      "第六布陣として予戦会を勝ち抜いた20組 出陣決定！",
      "",
      "",
      "AQA／AMOUR／究極人形／えすれある／OS☆K／キミニハネ／キュン!?恋堕ちキューピッド／SITRA.／Shupines／Cent Heaven／PrincessGarden-Nagoya-／Blancanie／ヒトノユメ／My Sugar Light／マイノリティアラート／Le☆miel／ミラクルファンファーレ！／もふる×クロス／LOVE 9 LOVE／Lily wonder(五十音順)"
    ],
    "urls": [],
    "img": ["https://sekigahara-idolwars.net/images/2024/home/home6.jpg"]
  },
  {
    "id": 6,
    "date": "2024.06.25",
    "title": "【第五布陣】出演者発表!!",
    "context": [
      "",
      "第五布陣として33組 出陣決定！",
      "",
      "",
      "AdanLilith／UPローチ／alma／【eN】／OS☆U／O2／カリスマめんざいふっ！／KissBee／逆転ねこぱんちっ！／けっぱって東北／KRD8／しろもん／C;ON／すたんぴっ！／すーぱーぷーばぁー!!／SAY-LA／月に足跡を残した6人の少女達は一体何を見たのか...／テラス×テラス／天使にはなれない／東京CuteCute／DREAMING MONSTER／ナナコロビヤオキ／NEO BREAK／蜂蜜★皇帝／Waltetto×School／蜜兎／パラディーク／P-Loco／MATANAGOYA／Milky＊Sphene／ミスティア！／Re:Clash(Candy☆Drops)／READY TO KISS (五十音順)"
    ],
    "urls": [],
    "img": ["https://sekigahara-idolwars.net/images/2024/home/home5.jpg"]
  },
  {
    "id": 5,
    "date": "2024.06.13",
    "title": "【第四布陣】出演者発表!!",
    "context": [
      "",
      "第四布陣として30組 出陣決定！",
      "",
      "",
      "iSPY／iLiFE!候補生／アキシブproject／Alcute！／泡沫パーティーズ／ゑんら／THE ENCORE／サクヤコノハナ／JAPANARIZM／Sharply♯ × Flutter♭／Symdolick／ZUTTOMOTTO／スポポポポニー／Chu-Z／twinpale／dela／テンシメシ／TENRIN／東京ガールズブラボー／#ドレミファソラシード／脳内パステル／Panic Monster !n Wonderland／フューチャーサイダー／ポンコツコンポ／#Mooove!／愛乙女☆DOLL(チームL)／ЯiＭ：ＭiＲ／RiNCENT#／ルルネージュ／わんふぁす！(五十音順)"
    ],
    "urls": [],
    "img": ["https://sekigahara-idolwars.net/images/2024/home/home4.jpg"]
  },
  {
    "id": 4,
    "date": "2024.06.11",
    "title": "【第三布陣】出演者発表!!",
    "context": [
      "",
      "第三布陣として30組 出演決定！",
      "",
      "",
      "I MY ME MINE／アップアップガールズ（仮）／アップアップガールズ（２）／アルテミスの翼／Ange☆Reve／ガガピエロ／君に、胸キュン。／GILTY×GILTY／ジエメイ／シュレーディンガーの犬／純情のアフィリア／シークレットシャノワール／Sweet Alley／SPRISE／SAISON／W.ダブルヴィ一／手羽先センセーション／点染テンセイ少女。／にっぽんワチャチャ／HIGH SPIRITS／Bunny La Crew／ハニースパイスRe.／PrincessGarden-姫庭-／Palette Parade／フルーティー／ベンジャス！／mistress／モノクローン／#よーよーよー／Onephony (五十音順)"
    ],
    "urls": [],
    "img": ["https://sekigahara-idolwars.net/images/2024/home/home3.jpg"]
  },
  {
    "id": 3,
    "date": "2024.06.07",
    "title": "【第二布陣】出演者発表!!",
    "context": [
      "",
      "第二布陣として15組 出演決定！",
      "",
      "",
      "i-COL／仮面女子／カラフルスクリーム／CANDY TUNE／九州女子翼／タイトル未定／2o Love to Sweet Bullet／なみだ色の消しごむ／#2i2／虹色の飛行少女／のんふぃく！／MyDearDarlin’／まねきケチャ／メイビーME／夜光性アミューズ (五十音順)"
    ],
    "urls": [],
    "img": ["https://sekigahara-idolwars.net/images/2024/home/home2.jpg"]
  },
  {
    "id": 2,
    "date": "2024.06.06",
    "title": "【第一布陣】出演者発表!!",
    "context": [
      "",
      "第一布陣として15組 出演決定！",
      "",
      "",
      "アイドルカレッジ／iLiFE!／かすみ草とステラ／JamsCollection／神使轟く、激情の如く。／シンデレラ宣言！／Task have Fun／ナナランド／なんキニ！／花いろは／#ババババンビ／Peel the Apple／FES☆TIVE／真っ白なキャンバス／ワンダーウィード 天 (五十音順)"
    ],
    "urls": [],
    "img": ["https://sekigahara-idolwars.net/images/2024/home/home1.jpg"]
  },
  {
    "id": 1,
    "date": "2024.02.25",
    "title": "関ケ原唄姫合戦2024　開催決定！！",
    "context": [
      "関ケ原唄姫合戦2024が19日（金）20日（土）21日（日）に開催します！！続報をお待ちください。"
    ],
    "urls": [],
    "img": []
  }
]
