{
  "date": "2024-07-19",
  "stageName": "4",
  "open": "9:00",
  "data": [
    {
      "id": 1,
      "startTime": "2024-07-19T02:20:00.000Z",
      "endTime": "2024-07-19T03:40:00.000Z",
      "artistName": "虹色の 飛行少女",
      "photo": false
    },
    {
      "id": 2,
      "startTime": "2024-07-19T03:45:00.000Z",
      "endTime": "2024-07-19T05:05:00.000Z",
      "artistName": "Sharply♯ × Flutter♭",
      "photo": false
    },
    {
      "id": 3,
      "startTime": "2024-07-19T05:10:00.000Z",
      "endTime": "2024-07-19T06:30:00.000Z",
      "artistName": "Palette Parade",
      "photo": false
    },
    {
      "id": 4,
      "startTime": "2024-07-19T07:40:00.000Z",
      "endTime": "2024-07-19T09:40:00.000Z",
      "artistName": "真っ白なキャンバス",
      "photo": false
    },
    {
      "id": 5,
      "startTime": "2024-07-19T10:30:00.000Z",
      "endTime": "2024-07-19T11:50:00.000Z",
      "artistName": "Palette Parade",
      "photo": false
    }
  ]
}